Metadata-Version: 1.0
Name: toasting-his-probability
Version: 0.1
Summary: Gaussian and Binomial distributions
Home-page: UNKNOWN
Author: James Jose
Author-email: jamesjose107@gmail.com
License: UNKNOWN
Platform: UNKNOWN
